slide/__init__.py
slide/authentication.py
slide/base_models.py
slide/household.py
slide/slides.py
slide/zones.py
slide_api_client-0.1.2.dist-info/LICENSE
slide_api_client-0.1.2.dist-info/METADATA
slide_api_client-0.1.2.dist-info/WHEEL
slide_api_client-0.1.2.dist-info/RECORD
