Metadata-Version: 2.1
Name: slide-api-client
Version: 0.1.2
Summary: Python library to communicate with the Slide API.
License: GNU General Public License v3.0
Author: Bart Hazen
Author-email: hazenbart@gmail.com
Requires-Python: >=3.10,<4.0
Classifier: License :: Other/Proprietary License
Classifier: Programming Language :: Python :: 3
Classifier: Programming Language :: Python :: 3.10
Classifier: Programming Language :: Python :: 3.11
Requires-Dist: aiohttp (>=3.8.4,<4.0.0)
